{
  "session_id": "27dfc37f-5e95-4677-a45d-27d8d586ead7",
  "agent_id": "technical_analysis_agent",
  "objective": "Identify technical patterns and signal confluences, focusing on after-hours developments and next-day preparation",
  "hypotheses_explored": 1,
  "research_plans_executed": 5,
  "patterns_identified": 0,
  "insights_generated": 0,
  "decision_tree": {
    "id": "29c87649-501b-431c-8630-0e506457cb92",
    "agent_name": "enhanced_technical_analysis_agent",
    "root_id": "03555ad3-8c7f-437a-8e2d-511fc6b436b3",
    "nodes": {
      "03555ad3-8c7f-437a-8e2d-511fc6b436b3": {
        "id": "03555ad3-8c7f-437a-8e2d-511fc6b436b3",
        "type": "root",
        "content": "Research Objective: Identify technical patterns and signal confluences, focusing on after-hours developments and next-day preparation",
        "data": {
          "objective": "Identify technical patterns and signal confluences, focusing on after-hours developments and next-day preparation",
          "context": {
            "market_data": {
              "indices": {},
              "market_sentiment": "neutral",
              "spy_daily_change": 0,
              "timestamp": "2025-07-09T18:06:43.071702",
              "data_source": "polygon_free_free_tier",
              "note": "Free tier: SPY only. Upgrade for full market overview (QQQ, IWM, VIX)",
              "premium_data": false
            },
            "timestamp": "2025-07-09T18:06:43.071719",
            "market_session": "after_hours",
            "symbols": [
              "SPY",
              "QQQ",
              "IWM",
              "TLT",
              "GLD",
              "VIX"
            ],
            "focus_timeframe": "short_to_medium_term"
          }
        },
        "parent_id": null,
        "children": [
          "75f27832-1076-48d1-bc3d-274b5122d381"
        ],
        "status": "pending",
        "confidence": 0.5,
        "created_at": "2025-07-09T18:06:43.072154",
        "updated_at": "2025-07-09T18:06:44.406947",
        "result": {}
      },
      "75f27832-1076-48d1-bc3d-274b5122d381": {
        "id": "75f27832-1076-48d1-bc3d-274b5122d381",
        "type": "hypothesis",
        "content": "Comprehensive analysis of Identify technical patterns and signal confluences, focusing on after-hours developments and next-day preparation",
        "data": {
          "exploration_priority": 1
        },
        "parent_id": "03555ad3-8c7f-437a-8e2d-511fc6b436b3",
        "children": [
          "298aa832-c0ce-4a2e-ab4e-c648ec2e4160",
          "c7b4bdc8-4b8b-4dc8-af89-6a276fab3e1b",
          "67f9c7b7-a4f8-4362-8c9b-b2c360928e69",
          "5eeef01e-f914-4e9e-a3f1-237d6ea0d560",
          "e1ddf59f-b60f-4389-b495-8f3b3b33ae2c"
        ],
        "status": "pending",
        "confidence": 0.5,
        "created_at": "2025-07-09T18:06:44.406941",
        "updated_at": "2025-07-09T18:06:44.408431",
        "result": {}
      },
      "298aa832-c0ce-4a2e-ab4e-c648ec2e4160": {
        "id": "298aa832-c0ce-4a2e-ab4e-c648ec2e4160",
        "type": "research",
        "content": "calculator: Statistical analysis of hypothesis variables",
        "data": {
          "description": "Statistical analysis of hypothesis variables",
          "type": "statistical_analysis",
          "executor": "<bound method EnhancedAutonomousAgent._execute_calculator_analysis of <agents.enhanced_autonomous_agent.EnhancedAutonomousAgent object at 0x137a56570>>",
          "parameters": {
            "analysis_type": "statistical",
            "hypothesis": "Comprehensive analysis of Identify technical patterns and signal confluences, focusing on after-hours developments and next-day preparation",
            "context": {
              "market_data": {
                "indices": {},
                "market_sentiment": "neutral",
                "spy_daily_change": 0,
                "timestamp": "2025-07-09T18:06:43.071702",
                "data_source": "polygon_free_free_tier",
                "note": "Free tier: SPY only. Upgrade for full market overview (QQQ, IWM, VIX)",
                "premium_data": false
              },
              "timestamp": "2025-07-09T18:06:43.071719",
              "market_session": "after_hours",
              "symbols": [
                "SPY",
                "QQQ",
                "IWM",
                "TLT",
                "GLD",
                "VIX"
              ],
              "focus_timeframe": "short_to_medium_term"
            }
          },
          "node_id": "298aa832-c0ce-4a2e-ab4e-c648ec2e4160",
          "tool_name": "calculator"
        },
        "parent_id": "75f27832-1076-48d1-bc3d-274b5122d381",
        "children": [],
        "status": "completed",
        "confidence": 0.1,
        "created_at": "2025-07-09T18:06:44.407215",
        "updated_at": "2025-07-09T18:42:02.419363",
        "result": {
          "error": "No data available for analysis",
          "confidence": 0.1
        }
      },
      "c7b4bdc8-4b8b-4dc8-af89-6a276fab3e1b": {
        "id": "c7b4bdc8-4b8b-4dc8-af89-6a276fab3e1b",
        "type": "research",
        "content": "calculator: Technical indicator calculations",
        "data": {
          "description": "Technical indicator calculations",
          "type": "technical_indicators",
          "executor": "<bound method EnhancedAutonomousAgent._execute_calculator_analysis of <agents.enhanced_autonomous_agent.EnhancedAutonomousAgent object at 0x137a56570>>",
          "parameters": {
            "analysis_type": "technical",
            "hypothesis": "Comprehensive analysis of Identify technical patterns and signal confluences, focusing on after-hours developments and next-day preparation",
            "context": {
              "market_data": {
                "indices": {},
                "market_sentiment": "neutral",
                "spy_daily_change": 0,
                "timestamp": "2025-07-09T18:06:43.071702",
                "data_source": "polygon_free_free_tier",
                "note": "Free tier: SPY only. Upgrade for full market overview (QQQ, IWM, VIX)",
                "premium_data": false
              },
              "timestamp": "2025-07-09T18:06:43.071719",
              "market_session": "after_hours",
              "symbols": [
                "SPY",
                "QQQ",
                "IWM",
                "TLT",
                "GLD",
                "VIX"
              ],
              "focus_timeframe": "short_to_medium_term"
            }
          },
          "node_id": "c7b4bdc8-4b8b-4dc8-af89-6a276fab3e1b",
          "tool_name": "calculator"
        },
        "parent_id": "75f27832-1076-48d1-bc3d-274b5122d381",
        "children": [],
        "status": "completed",
        "confidence": 0.1,
        "created_at": "2025-07-09T18:06:44.407402",
        "updated_at": "2025-07-09T18:42:17.424772",
        "result": {
          "error": "No data available for analysis",
          "confidence": 0.1
        }
      },
      "67f9c7b7-a4f8-4362-8c9b-b2c360928e69": {
        "id": "67f9c7b7-a4f8-4362-8c9b-b2c360928e69",
        "type": "research",
        "content": "data_fetcher: Real-time market data analysis",
        "data": {
          "description": "Real-time market data analysis",
          "type": "market_data",
          "executor": "<bound method EnhancedAutonomousAgent._execute_market_data_analysis of <agents.enhanced_autonomous_agent.EnhancedAutonomousAgent object at 0x137a56570>>",
          "parameters": {
            "data_type": "real_time",
            "hypothesis": "Comprehensive analysis of Identify technical patterns and signal confluences, focusing on after-hours developments and next-day preparation",
            "context": {
              "market_data": {
                "indices": {},
                "market_sentiment": "neutral",
                "spy_daily_change": 0,
                "timestamp": "2025-07-09T18:06:43.071702",
                "data_source": "polygon_free_free_tier",
                "note": "Free tier: SPY only. Upgrade for full market overview (QQQ, IWM, VIX)",
                "premium_data": false
              },
              "timestamp": "2025-07-09T18:06:43.071719",
              "market_session": "after_hours",
              "symbols": [
                "SPY",
                "QQQ",
                "IWM",
                "TLT",
                "GLD",
                "VIX"
              ],
              "focus_timeframe": "short_to_medium_term"
            }
          },
          "node_id": "67f9c7b7-a4f8-4362-8c9b-b2c360928e69",
          "tool_name": "data_fetcher"
        },
        "parent_id": "75f27832-1076-48d1-bc3d-274b5122d381",
        "children": [],
        "status": "completed",
        "confidence": 0.8,
        "created_at": "2025-07-09T18:06:44.408027",
        "updated_at": "2025-07-09T18:45:17.516370",
        "result": {
          "tool": "data_fetcher",
          "data_type": "real_time",
          "results": {
            "market_overview": {
              "indices": {},
              "market_sentiment": "neutral",
              "spy_daily_change": 0,
              "timestamp": "2025-07-09T18:42:32.440120",
              "data_source": "polygon_free_free_tier",
              "note": "Free tier: SPY only. Upgrade for full market overview (QQQ, IWM, VIX)",
              "premium_data": false
            },
            "sector_data": {
              "Technology": {
                "error": "No data source available for XLK",
                "data": null
              },
              "Healthcare": {
                "error": "No data source available for XLV",
                "data": null
              },
              "Financial": {
                "error": "No data source available for XLF",
                "data": null
              },
              "Consumer Discretionary": {
                "error": "No data source available for XLY",
                "data": null
              },
              "Communication Services": {
                "error": "No data source available for XLC",
                "data": null
              },
              "Industrials": {
                "error": "No data source available for XLI",
                "data": null
              },
              "Consumer Staples": {
                "error": "No data source available for XLP",
                "data": null
              },
              "Energy": {
                "error": "No data source available for XLE",
                "data": null
              },
              "Utilities": {
                "error": "No data source available for XLU",
                "data": null
              },
              "Real Estate": {
                "error": "No data source available for XLRE",
                "data": null
              },
              "Materials": {
                "error": "No data source available for XLB",
                "data": null
              }
            }
          },
          "confidence": 0.8,
          "insights": [
            "Market data analysis for "
          ]
        }
      },
      "5eeef01e-f914-4e9e-a3f1-237d6ea0d560": {
        "id": "5eeef01e-f914-4e9e-a3f1-237d6ea0d560",
        "type": "research",
        "content": "data_fetcher: Historical data pattern analysis",
        "data": {
          "description": "Historical data pattern analysis",
          "type": "historical_analysis",
          "executor": "<bound method EnhancedAutonomousAgent._execute_market_data_analysis of <agents.enhanced_autonomous_agent.EnhancedAutonomousAgent object at 0x137a56570>>",
          "parameters": {
            "data_type": "historical",
            "hypothesis": "Comprehensive analysis of Identify technical patterns and signal confluences, focusing on after-hours developments and next-day preparation",
            "context": {
              "market_data": {
                "indices": {},
                "market_sentiment": "neutral",
                "spy_daily_change": 0,
                "timestamp": "2025-07-09T18:06:43.071702",
                "data_source": "polygon_free_free_tier",
                "note": "Free tier: SPY only. Upgrade for full market overview (QQQ, IWM, VIX)",
                "premium_data": false
              },
              "timestamp": "2025-07-09T18:06:43.071719",
              "market_session": "after_hours",
              "symbols": [
                "SPY",
                "QQQ",
                "IWM",
                "TLT",
                "GLD",
                "VIX"
              ],
              "focus_timeframe": "short_to_medium_term"
            }
          },
          "node_id": "5eeef01e-f914-4e9e-a3f1-237d6ea0d560",
          "tool_name": "data_fetcher"
        },
        "parent_id": "75f27832-1076-48d1-bc3d-274b5122d381",
        "children": [],
        "status": "completed",
        "confidence": 0.8,
        "created_at": "2025-07-09T18:06:44.408256",
        "updated_at": "2025-07-09T18:48:17.586450",
        "result": {
          "tool": "data_fetcher",
          "data_type": "real_time",
          "results": {
            "market_overview": {
              "indices": {},
              "market_sentiment": "neutral",
              "spy_daily_change": 0,
              "timestamp": "2025-07-09T18:45:32.524676",
              "data_source": "polygon_free_free_tier",
              "note": "Free tier: SPY only. Upgrade for full market overview (QQQ, IWM, VIX)",
              "premium_data": false
            },
            "sector_data": {
              "Technology": {
                "error": "No data source available for XLK",
                "data": null
              },
              "Healthcare": {
                "error": "No data source available for XLV",
                "data": null
              },
              "Financial": {
                "error": "No data source available for XLF",
                "data": null
              },
              "Consumer Discretionary": {
                "error": "No data source available for XLY",
                "data": null
              },
              "Communication Services": {
                "error": "No data source available for XLC",
                "data": null
              },
              "Industrials": {
                "error": "No data source available for XLI",
                "data": null
              },
              "Consumer Staples": {
                "error": "No data source available for XLP",
                "data": null
              },
              "Energy": {
                "error": "No data source available for XLE",
                "data": null
              },
              "Utilities": {
                "error": "No data source available for XLU",
                "data": null
              },
              "Real Estate": {
                "error": "No data source available for XLRE",
                "data": null
              },
              "Materials": {
                "error": "No data source available for XLB",
                "data": null
              }
            }
          },
          "confidence": 0.8,
          "insights": [
            "Market data analysis for "
          ]
        }
      },
      "e1ddf59f-b60f-4389-b495-8f3b3b33ae2c": {
        "id": "e1ddf59f-b60f-4389-b495-8f3b3b33ae2c",
        "type": "research",
        "content": "rag_agent: Retrieve similar research patterns",
        "data": {
          "description": "Retrieve similar research patterns",
          "type": "pattern_retrieval",
          "executor": "<bound method EnhancedAutonomousAgent._execute_memory_lookup of <agents.enhanced_autonomous_agent.EnhancedAutonomousAgent object at 0x137a56570>>",
          "parameters": {
            "lookup_type": "patterns",
            "hypothesis": "Comprehensive analysis of Identify technical patterns and signal confluences, focusing on after-hours developments and next-day preparation",
            "context": {
              "market_data": {
                "indices": {},
                "market_sentiment": "neutral",
                "spy_daily_change": 0,
                "timestamp": "2025-07-09T18:06:43.071702",
                "data_source": "polygon_free_free_tier",
                "note": "Free tier: SPY only. Upgrade for full market overview (QQQ, IWM, VIX)",
                "premium_data": false
              },
              "timestamp": "2025-07-09T18:06:43.071719",
              "market_session": "after_hours",
              "symbols": [
                "SPY",
                "QQQ",
                "IWM",
                "TLT",
                "GLD",
                "VIX"
              ],
              "focus_timeframe": "short_to_medium_term"
            }
          },
          "node_id": "e1ddf59f-b60f-4389-b495-8f3b3b33ae2c",
          "tool_name": "rag_agent"
        },
        "parent_id": "75f27832-1076-48d1-bc3d-274b5122d381",
        "children": [],
        "status": "completed",
        "confidence": 0.1,
        "created_at": "2025-07-09T18:06:44.408428",
        "updated_at": "2025-07-09T18:48:18.933241",
        "result": {
          "error": "Connection error. in query.",
          "confidence": 0.1
        }
      }
    },
    "best_path": null,
    "best_confidence": 0.0,
    "summary": {
      "tree_id": "29c87649-501b-431c-8630-0e506457cb92",
      "agent_name": "enhanced_technical_analysis_agent",
      "total_nodes": 7,
      "by_status": {
        "pending": 2,
        "completed": 5
      },
      "by_type": {
        "root": 1,
        "hypothesis": 1,
        "research": 5
      },
      "best_confidence": 0.0,
      "active_leaves": 0
    }
  },
  "insights": [],
  "competitive_edges": [],
  "timestamp": "2025-07-09T18:54:59.378426",
  "session_duration": "research_complete",
  "research_track": "technical_analysis",
  "specialization": "technical_analysis",
  "market_context": {
    "market_data": {
      "indices": {},
      "market_sentiment": "neutral",
      "spy_daily_change": 0,
      "timestamp": "2025-07-09T18:06:43.071702",
      "data_source": "polygon_free_free_tier",
      "note": "Free tier: SPY only. Upgrade for full market overview (QQQ, IWM, VIX)",
      "premium_data": false
    },
    "timestamp": "2025-07-09T18:06:43.071719",
    "market_session": "after_hours",
    "symbols": [
      "SPY",
      "QQQ",
      "IWM",
      "TLT",
      "GLD",
      "VIX"
    ],
    "focus_timeframe": "short_to_medium_term"
  },
  "completed_at": "2025-07-09T18:54:59.378602"
}